stl_stretch/__init__.py
stl_stretch-0.1.dist-info/COPYING
stl_stretch-0.1.dist-info/METADATA
stl_stretch-0.1.dist-info/WHEEL
stl_stretch-0.1.dist-info/entry_points.txt
stl_stretch-0.1.dist-info/top_level.txt
stl_stretch-0.1.dist-info/RECORD
