Metadata-Version: 2.1
Name: stl-stretch
Version: 0.1
Summary: Stretches just part of an stl file
Home-page: https://github.com/thatch/stl_stretch
Author: Tim Hatch
Author-email: tim@timhatch.com
License: BSD
Platform: UNKNOWN
